narpyn/__init__.py
narpyn/ona/__init__.py
narpyn/ona/nar.py
narpyn/ona/narsese.py
narpyn/ona/NAR/__init__.py
narpyn-0.2.0.dist-info/METADATA
narpyn-0.2.0.dist-info/WHEEL
narpyn-0.2.0.dist-info/licenses/LICENSE
narpyn-0.2.0.dist-info/RECORD
