Metadata-Version: 2.1
Name: narpyn
Version: 0.2.0
Summary: A Python API library for NARS
Project-URL: Homepage, https://ntoxeg.github.io/narpyn/
Project-URL: Sponsor, https://github.com/sponsors/ntoxeg
Project-URL: Tracker, https://github.com/ntoxeg/narpyn/issues
Project-URL: Source, https://github.com/ntoxeg/narpyn
Author-email: Adrian Borucki <ab@synthillect.ai>
License-Expression: Apache-2.0
License-File: LICENSE
Keywords: ai,nars
Classifier: Development Status :: 3 - Alpha
Classifier: License :: OSI Approved :: Apache Software License
Classifier: Programming Language :: Python
Classifier: Programming Language :: Python :: 3.10
Classifier: Programming Language :: Python :: 3.11
Classifier: Programming Language :: Python :: Implementation :: CPython
Requires-Python: >=3.10
Requires-Dist: ona>=0.9.2
